{
  "meta": {
    "tool": "mamekit",
    "version": "0.1.0",
    "mameSrc": "/Users/benbruscella/Projects/Github/mame",
    "driverFile": "src/mame/galaxian/galaxian.cpp",
    "generatedAt": "2026-07-19T06:32:47.289Z",
    "license": "BSD-3-Clause",
    "copyrightHolders": "Aaron Giles, Couriersud, Stephane Humbert, Robbbert"
  },
  "nodes": [
    {
      "id": "file:src/mame/galaxian/galaxian.cpp",
      "label": "SourceFile",
      "props": {
        "path": "src/mame/galaxian/galaxian.cpp"
      }
    },
    {
      "id": "file:emu.h",
      "label": "SourceFile",
      "props": {
        "path": "emu.h",
        "external": true
      }
    },
    {
      "id": "file:galaxian.h",
      "label": "SourceFile",
      "props": {
        "path": "galaxian.h",
        "external": true
      }
    },
    {
      "id": "file:galaxian_a.h",
      "label": "SourceFile",
      "props": {
        "path": "galaxian_a.h",
        "external": true
      }
    },
    {
      "id": "file:cclimber_a.h",
      "label": "SourceFile",
      "props": {
        "path": "cclimber_a.h",
        "external": true
      }
    },
    {
      "id": "file:cpu/m6502/m6502.h",
      "label": "SourceFile",
      "props": {
        "path": "cpu/m6502/m6502.h",
        "external": true
      }
    },
    {
      "id": "file:cpu/s2650/s2650.h",
      "label": "SourceFile",
      "props": {
        "path": "cpu/s2650/s2650.h",
        "external": true
      }
    },
    {
      "id": "file:cpu/z80/z80.h",
      "label": "SourceFile",
      "props": {
        "path": "cpu/z80/z80.h",
        "external": true
      }
    },
    {
      "id": "file:machine/nvram.h",
      "label": "SourceFile",
      "props": {
        "path": "machine/nvram.h",
        "external": true
      }
    },
    {
      "id": "file:machine/watchdog.h",
      "label": "SourceFile",
      "props": {
        "path": "machine/watchdog.h",
        "external": true
      }
    },
    {
      "id": "file:screen.h",
      "label": "SourceFile",
      "props": {
        "path": "screen.h",
        "external": true
      }
    },
    {
      "id": "file:speaker.h",
      "label": "SourceFile",
      "props": {
        "path": "speaker.h",
        "external": true
      }
    },
    {
      "id": "file:nl_konami.h",
      "label": "SourceFile",
      "props": {
        "path": "nl_konami.h",
        "external": true
      }
    },
    {
      "id": "game:galaxian",
      "label": "Game",
      "props": {
        "name": "galaxian",
        "year": "1979",
        "company": "Namco",
        "fullname": "Galaxian (Namco set 1)",
        "monitor": "ROT90",
        "cls": "galaxian_state",
        "init": "init_galaxian",
        "flags": "MACHINE_SUPPORTS_SAVE",
        "kind": "arcade"
      }
    },
    {
      "id": "romset:galaxian",
      "label": "RomSet",
      "props": {
        "name": "galaxian"
      }
    },
    {
      "id": "region:galaxian/maincpu",
      "label": "RomRegion",
      "props": {
        "tag": "maincpu",
        "size": 16384,
        "flags": "0"
      }
    },
    {
      "id": "rom:galaxian/maincpu/galmidw.u",
      "label": "Rom",
      "props": {
        "file": "galmidw.u",
        "offset": 0,
        "size": 2048,
        "crc": "745e2d61",
        "sha1": "e65f74e35b1bfaccd407e168ea55678ae9b68edf"
      }
    },
    {
      "id": "rom:galaxian/maincpu/galmidw.v",
      "label": "Rom",
      "props": {
        "file": "galmidw.v",
        "offset": 2048,
        "size": 2048,
        "crc": "9c999a40",
        "sha1": "02fdcd95d8511e64c0d2b007b874112d53e41045"
      }
    },
    {
      "id": "rom:galaxian/maincpu/galmidw.w",
      "label": "Rom",
      "props": {
        "file": "galmidw.w",
        "offset": 4096,
        "size": 2048,
        "crc": "b5894925",
        "sha1": "0046b9ed697a34d088de1aead8bd7cbe526a2396"
      }
    },
    {
      "id": "rom:galaxian/maincpu/galmidw.y",
      "label": "Rom",
      "props": {
        "file": "galmidw.y",
        "offset": 6144,
        "size": 2048,
        "crc": "6b3ca10b",
        "sha1": "18d8714e5ef52f63ba8888ecc5a25b17b3bf17d1"
      }
    },
    {
      "id": "rom:galaxian/maincpu/7l",
      "label": "Rom",
      "props": {
        "file": "7l",
        "offset": 8192,
        "size": 2048,
        "crc": "1b933207",
        "sha1": "8b44b0f74420871454e27894d0f004859f9e59a9"
      }
    },
    {
      "id": "region:galaxian/gfx1",
      "label": "RomRegion",
      "props": {
        "tag": "gfx1",
        "size": 4096,
        "flags": "0"
      }
    },
    {
      "id": "rom:galaxian/gfx1/1h.bin",
      "label": "Rom",
      "props": {
        "file": "1h.bin",
        "offset": 0,
        "size": 2048,
        "crc": "39fb43a4",
        "sha1": "4755609bd974976f04855d51e08ec0d62ab4bc07"
      }
    },
    {
      "id": "rom:galaxian/gfx1/1k.bin",
      "label": "Rom",
      "props": {
        "file": "1k.bin",
        "offset": 2048,
        "size": 2048,
        "crc": "7e3f56a2",
        "sha1": "a9795d8b7388f404f3b0e2c6ce15d713a4c5bafa"
      }
    },
    {
      "id": "region:galaxian/proms",
      "label": "RomRegion",
      "props": {
        "tag": "proms",
        "size": 32,
        "flags": "0"
      }
    },
    {
      "id": "rom:galaxian/proms/6l.bpr",
      "label": "Rom",
      "props": {
        "file": "6l.bpr",
        "offset": 0,
        "size": 32,
        "crc": "c3ac9467",
        "sha1": "f382ad5a34d282056c78a5ec00c30ec43772bae2"
      }
    },
    {
      "id": "map:galaxian_state.galaxian_map_discrete",
      "label": "AddressMap",
      "props": {
        "cls": "galaxian_state",
        "name": "galaxian_map_discrete"
      }
    },
    {
      "id": "map:galaxian_state.galaxian_map_discrete/range0",
      "label": "AddressRange",
      "props": {
        "start": 24580,
        "end": 24583,
        "raw": "map(0x6004, 0x6007).mirror(0x07f8).w(\"cust\", FUNC(galaxian_sound_device::lfo_freq_w))",
        "mirror": 2040
      }
    },
    {
      "id": "handler:galaxian_sound_device.lfo_freq_w",
      "label": "Handler",
      "props": {
        "method": "lfo_freq_w",
        "ownerClass": "galaxian_sound_device"
      }
    },
    {
      "id": "map:galaxian_state.galaxian_map_discrete/range1",
      "label": "AddressRange",
      "props": {
        "start": 26624,
        "end": 26631,
        "raw": "map(0x6800, 0x6807).mirror(0x07f8).w(\"cust\", FUNC(galaxian_sound_device::sound_w))",
        "mirror": 2040
      }
    },
    {
      "id": "handler:galaxian_sound_device.sound_w",
      "label": "Handler",
      "props": {
        "method": "sound_w",
        "ownerClass": "galaxian_sound_device"
      }
    },
    {
      "id": "map:galaxian_state.galaxian_map_discrete/range2",
      "label": "AddressRange",
      "props": {
        "start": 30720,
        "end": 30720,
        "raw": "map(0x7800, 0x7800).mirror(0x07ff).w(\"cust\", FUNC(galaxian_sound_device::pitch_w))",
        "mirror": 2047
      }
    },
    {
      "id": "handler:galaxian_sound_device.pitch_w",
      "label": "Handler",
      "props": {
        "method": "pitch_w",
        "ownerClass": "galaxian_sound_device"
      }
    },
    {
      "id": "map:galaxian_state.galaxian_map_base",
      "label": "AddressMap",
      "props": {
        "cls": "galaxian_state",
        "name": "galaxian_map_base",
        "unmapHigh": true
      }
    },
    {
      "id": "map:galaxian_state.galaxian_map_base/range0",
      "label": "AddressRange",
      "props": {
        "start": 0,
        "end": 16383,
        "raw": "map(0x0000, 0x3fff).rom()",
        "rom": true
      }
    },
    {
      "id": "map:galaxian_state.galaxian_map_base/range1",
      "label": "AddressRange",
      "props": {
        "start": 16384,
        "end": 17407,
        "raw": "map(0x4000, 0x43ff).mirror(0x0400).ram()",
        "mirror": 1024,
        "ram": true
      }
    },
    {
      "id": "map:galaxian_state.galaxian_map_base/range2",
      "label": "AddressRange",
      "props": {
        "start": 20480,
        "end": 21503,
        "raw": "map(0x5000, 0x53ff).mirror(0x0400).ram().w(FUNC(galaxian_state::galaxian_videoram_w)).share(\"videoram\")",
        "mirror": 1024,
        "ram": true,
        "share": "videoram"
      }
    },
    {
      "id": "handler:galaxian_state.galaxian_videoram_w",
      "label": "Handler",
      "props": {
        "method": "galaxian_videoram_w",
        "ownerClass": "galaxian_state"
      }
    },
    {
      "id": "map:galaxian_state.galaxian_map_base/range3",
      "label": "AddressRange",
      "props": {
        "start": 22528,
        "end": 22783,
        "raw": "map(0x5800, 0x58ff).mirror(0x0700).ram().w(FUNC(galaxian_state::galaxian_objram_w)).share(\"spriteram\")",
        "mirror": 1792,
        "ram": true,
        "share": "spriteram"
      }
    },
    {
      "id": "handler:galaxian_state.galaxian_objram_w",
      "label": "Handler",
      "props": {
        "method": "galaxian_objram_w",
        "ownerClass": "galaxian_state"
      }
    },
    {
      "id": "map:galaxian_state.galaxian_map_base/range4",
      "label": "AddressRange",
      "props": {
        "start": 24576,
        "end": 24576,
        "raw": "map(0x6000, 0x6000).mirror(0x07ff).portr(\"IN0\")",
        "mirror": 2047,
        "portRead": "IN0"
      }
    },
    {
      "id": "map:galaxian_state.galaxian_map_base/range5",
      "label": "AddressRange",
      "props": {
        "start": 24576,
        "end": 24577,
        "raw": "map(0x6000, 0x6001).mirror(0x07f8).w(FUNC(galaxian_state::start_lamp_w))",
        "mirror": 2040
      }
    },
    {
      "id": "handler:galaxian_state.start_lamp_w",
      "label": "Handler",
      "props": {
        "method": "start_lamp_w",
        "ownerClass": "galaxian_state"
      }
    },
    {
      "id": "map:galaxian_state.galaxian_map_base/range6",
      "label": "AddressRange",
      "props": {
        "start": 24578,
        "end": 24578,
        "raw": "map(0x6002, 0x6002).mirror(0x07f8).w(FUNC(galaxian_state::coin_lock_w))",
        "mirror": 2040
      }
    },
    {
      "id": "handler:galaxian_state.coin_lock_w",
      "label": "Handler",
      "props": {
        "method": "coin_lock_w",
        "ownerClass": "galaxian_state"
      }
    },
    {
      "id": "map:galaxian_state.galaxian_map_base/range7",
      "label": "AddressRange",
      "props": {
        "start": 24579,
        "end": 24579,
        "raw": "map(0x6003, 0x6003).mirror(0x07f8).w(FUNC(galaxian_state::coin_count_0_w))",
        "mirror": 2040
      }
    },
    {
      "id": "handler:galaxian_state.coin_count_0_w",
      "label": "Handler",
      "props": {
        "method": "coin_count_0_w",
        "ownerClass": "galaxian_state"
      }
    },
    {
      "id": "map:galaxian_state.galaxian_map_base/range8",
      "label": "AddressRange",
      "props": {
        "start": 26624,
        "end": 26624,
        "raw": "map(0x6800, 0x6800).mirror(0x07ff).portr(\"IN1\")",
        "mirror": 2047,
        "portRead": "IN1"
      }
    },
    {
      "id": "map:galaxian_state.galaxian_map_base/range9",
      "label": "AddressRange",
      "props": {
        "start": 28672,
        "end": 28672,
        "raw": "map(0x7000, 0x7000).mirror(0x07ff).portr(\"IN2\")",
        "mirror": 2047,
        "portRead": "IN2"
      }
    },
    {
      "id": "map:galaxian_state.galaxian_map_base/range10",
      "label": "AddressRange",
      "props": {
        "start": 28673,
        "end": 28673,
        "raw": "map(0x7001, 0x7001).mirror(0x07f8).w(FUNC(galaxian_state::irq_enable_w))",
        "mirror": 2040
      }
    },
    {
      "id": "handler:galaxian_state.irq_enable_w",
      "label": "Handler",
      "props": {
        "method": "irq_enable_w",
        "ownerClass": "galaxian_state"
      }
    },
    {
      "id": "map:galaxian_state.galaxian_map_base/range11",
      "label": "AddressRange",
      "props": {
        "start": 28676,
        "end": 28676,
        "raw": "map(0x7004, 0x7004).mirror(0x07f8).w(FUNC(galaxian_state::galaxian_stars_enable_w))",
        "mirror": 2040
      }
    },
    {
      "id": "handler:galaxian_state.galaxian_stars_enable_w",
      "label": "Handler",
      "props": {
        "method": "galaxian_stars_enable_w",
        "ownerClass": "galaxian_state"
      }
    },
    {
      "id": "map:galaxian_state.galaxian_map_base/range12",
      "label": "AddressRange",
      "props": {
        "start": 28678,
        "end": 28678,
        "raw": "map(0x7006, 0x7006).mirror(0x07f8).w(FUNC(galaxian_state::galaxian_flip_screen_x_w))",
        "mirror": 2040
      }
    },
    {
      "id": "handler:galaxian_state.galaxian_flip_screen_x_w",
      "label": "Handler",
      "props": {
        "method": "galaxian_flip_screen_x_w",
        "ownerClass": "galaxian_state"
      }
    },
    {
      "id": "map:galaxian_state.galaxian_map_base/range13",
      "label": "AddressRange",
      "props": {
        "start": 28679,
        "end": 28679,
        "raw": "map(0x7007, 0x7007).mirror(0x07f8).w(FUNC(galaxian_state::galaxian_flip_screen_y_w))",
        "mirror": 2040
      }
    },
    {
      "id": "handler:galaxian_state.galaxian_flip_screen_y_w",
      "label": "Handler",
      "props": {
        "method": "galaxian_flip_screen_y_w",
        "ownerClass": "galaxian_state"
      }
    },
    {
      "id": "map:galaxian_state.galaxian_map_base/range14",
      "label": "AddressRange",
      "props": {
        "start": 30720,
        "end": 30720,
        "raw": "map(0x7800, 0x7800).mirror(0x07ff).r(\"watchdog\", FUNC(watchdog_timer_device::reset_r))",
        "mirror": 2047
      }
    },
    {
      "id": "handler:watchdog_timer_device.reset_r",
      "label": "Handler",
      "props": {
        "method": "reset_r",
        "ownerClass": "watchdog_timer_device"
      }
    },
    {
      "id": "map:galaxian_state.galaxian_map",
      "label": "AddressMap",
      "props": {
        "cls": "galaxian_state",
        "name": "galaxian_map",
        "calls": [
          "galaxian_map_base",
          "galaxian_map_discrete"
        ]
      }
    },
    {
      "id": "machine:galaxian_state.galaxian_base",
      "label": "MachineConfig",
      "props": {
        "cls": "galaxian_state",
        "name": "galaxian_base",
        "calls": []
      }
    },
    {
      "id": "device:galaxian_state.galaxian_base/maincpu",
      "label": "Device",
      "props": {
        "type": "Z80",
        "tag": "maincpu",
        "clock": 3072000,
        "config": [
          "Z80(config, m_maincpu, GALAXIAN_PIXEL_CLOCK/3/2)",
          "m_maincpu->set_addrmap(AS_PROGRAM, &galaxian_state::galaxian_map)"
        ]
      }
    },
    {
      "id": "device:galaxian_state.galaxian_base/watchdog",
      "label": "Device",
      "props": {
        "type": "WATCHDOG_TIMER",
        "tag": "watchdog",
        "clock": null,
        "config": [
          "WATCHDOG_TIMER(config, \"watchdog\").set_vblank_count(\"screen\", 8)"
        ]
      }
    },
    {
      "id": "device:galaxian_state.galaxian_base/gfxdecode",
      "label": "Device",
      "props": {
        "type": "GFXDECODE",
        "tag": "gfxdecode",
        "clock": null,
        "config": [
          "GFXDECODE(config, m_gfxdecode, m_palette, gfx_galaxian)"
        ],
        "clockExpr": "m_palette, gfx_galaxian"
      }
    },
    {
      "id": "device:galaxian_state.galaxian_base/palette",
      "label": "Device",
      "props": {
        "type": "PALETTE",
        "tag": "palette",
        "clock": null,
        "config": [
          "PALETTE(config, m_palette, FUNC(galaxian_state::galaxian_palette), 32)"
        ],
        "clockExpr": "FUNC(galaxian_state::galaxian_palette), 32"
      }
    },
    {
      "id": "device:galaxian_state.galaxian_base/screen",
      "label": "Device",
      "props": {
        "type": "SCREEN",
        "tag": "screen",
        "clock": null,
        "config": [
          "SCREEN(config, m_screen, SCREEN_TYPE_RASTER)",
          "m_screen->set_raw(GALAXIAN_PIXEL_CLOCK, GALAXIAN_HTOTAL, GALAXIAN_HBEND, GALAXIAN_HBSTART, GALAXIAN_VTOTAL, GALAXIAN_VBEND, GALAXIAN_VBSTART)",
          "m_screen->set_screen_update(FUNC(galaxian_state::screen_update_galaxian))",
          "m_screen->screen_vblank().set(FUNC(galaxian_state::vblank_interrupt_w))"
        ],
        "clockExpr": "SCREEN_TYPE_RASTER",
        "screenRaw": [
          18432000,
          1152,
          0,
          768,
          264,
          16,
          240
        ]
      }
    },
    {
      "id": "device:galaxian_state.galaxian_base/speaker",
      "label": "Device",
      "props": {
        "type": "SPEAKER",
        "tag": "speaker",
        "clock": null,
        "config": [
          "SPEAKER(config, \"speaker\").front_center()"
        ]
      }
    },
    {
      "id": "machine:galaxian_state.galaxian",
      "label": "MachineConfig",
      "props": {
        "cls": "galaxian_state",
        "name": "galaxian",
        "calls": [
          "galaxian_base"
        ]
      }
    },
    {
      "id": "device:galaxian_state.galaxian/cust",
      "label": "Device",
      "props": {
        "type": "GALAXIAN_SOUND",
        "tag": "cust",
        "clock": 0,
        "config": [
          "GALAXIAN_SOUND(config, \"cust\")"
        ]
      }
    },
    {
      "id": "machine:galaxian_sound_device.device_add_mconfig",
      "label": "MachineConfig",
      "props": {
        "cls": "galaxian_sound_device",
        "name": "device_add_mconfig",
        "calls": []
      }
    },
    {
      "id": "device:galaxian_sound_device.device_add_mconfig/discrete",
      "label": "Device",
      "props": {
        "type": "DISCRETE",
        "tag": "discrete",
        "clock": null,
        "config": [
          "DISCRETE(config, m_discrete).add_route(ALL_OUTPUTS, \":speaker\", 1.0)",
          "m_discrete->set_intf(galaxian_discrete)"
        ]
      }
    },
    {
      "id": "inputs:galaxian",
      "label": "InputPorts",
      "props": {
        "name": "galaxian"
      }
    },
    {
      "id": "inputs:galaxian/IN0",
      "label": "Port",
      "props": {
        "tag": "IN0",
        "modify": false
      }
    },
    {
      "id": "inputs:galaxian/IN0/f0",
      "label": "PortField",
      "props": {
        "kind": "bit",
        "mask": 1,
        "activeLow": false,
        "type": "IPT_COIN1"
      }
    },
    {
      "id": "inputs:galaxian/IN0/f1",
      "label": "PortField",
      "props": {
        "kind": "bit",
        "mask": 2,
        "activeLow": false,
        "type": "IPT_COIN2"
      }
    },
    {
      "id": "inputs:galaxian/IN0/f2",
      "label": "PortField",
      "props": {
        "kind": "bit",
        "mask": 4,
        "activeLow": false,
        "type": "IPT_JOYSTICK_LEFT",
        "modifiers": [
          "PORT_2WAY"
        ]
      }
    },
    {
      "id": "inputs:galaxian/IN0/f3",
      "label": "PortField",
      "props": {
        "kind": "bit",
        "mask": 8,
        "activeLow": false,
        "type": "IPT_JOYSTICK_RIGHT",
        "modifiers": [
          "PORT_2WAY"
        ]
      }
    },
    {
      "id": "inputs:galaxian/IN0/f4",
      "label": "PortField",
      "props": {
        "kind": "bit",
        "mask": 16,
        "activeLow": false,
        "type": "IPT_BUTTON1"
      }
    },
    {
      "id": "inputs:galaxian/IN0/f5",
      "label": "PortField",
      "props": {
        "kind": "dip",
        "mask": 32,
        "name": "Cabinet",
        "defaultValue": 0,
        "settings": [
          "0=Upright",
          "32=Cocktail"
        ]
      }
    },
    {
      "id": "inputs:galaxian/IN0/f6",
      "label": "PortField",
      "props": {
        "kind": "service",
        "mask": 64,
        "activeLow": false
      }
    },
    {
      "id": "inputs:galaxian/IN0/f7",
      "label": "PortField",
      "props": {
        "kind": "bit",
        "mask": 128,
        "activeLow": false,
        "type": "IPT_SERVICE1"
      }
    },
    {
      "id": "inputs:galaxian/IN1",
      "label": "Port",
      "props": {
        "tag": "IN1",
        "modify": false
      }
    },
    {
      "id": "inputs:galaxian/IN1/f0",
      "label": "PortField",
      "props": {
        "kind": "bit",
        "mask": 1,
        "activeLow": false,
        "type": "IPT_START1"
      }
    },
    {
      "id": "inputs:galaxian/IN1/f1",
      "label": "PortField",
      "props": {
        "kind": "bit",
        "mask": 2,
        "activeLow": false,
        "type": "IPT_START2"
      }
    },
    {
      "id": "inputs:galaxian/IN1/f2",
      "label": "PortField",
      "props": {
        "kind": "bit",
        "mask": 4,
        "activeLow": false,
        "type": "IPT_JOYSTICK_LEFT",
        "modifiers": [
          "PORT_2WAY",
          "PORT_COCKTAIL"
        ]
      }
    },
    {
      "id": "inputs:galaxian/IN1/f3",
      "label": "PortField",
      "props": {
        "kind": "bit",
        "mask": 8,
        "activeLow": false,
        "type": "IPT_JOYSTICK_RIGHT",
        "modifiers": [
          "PORT_2WAY",
          "PORT_COCKTAIL"
        ]
      }
    },
    {
      "id": "inputs:galaxian/IN1/f4",
      "label": "PortField",
      "props": {
        "kind": "bit",
        "mask": 16,
        "activeLow": false,
        "type": "IPT_BUTTON1",
        "modifiers": [
          "PORT_COCKTAIL"
        ]
      }
    },
    {
      "id": "inputs:galaxian/IN1/f5",
      "label": "PortField",
      "props": {
        "kind": "bit",
        "mask": 32,
        "activeLow": false,
        "type": "IPT_UNUSED"
      }
    },
    {
      "id": "inputs:galaxian/IN1/f6",
      "label": "PortField",
      "props": {
        "kind": "dip",
        "mask": 192,
        "name": "Coinage",
        "defaultValue": 0,
        "settings": [
          "64=2C 1C",
          "0=1C 1C",
          "128=1C 2C",
          "192=Free Play"
        ]
      }
    },
    {
      "id": "inputs:galaxian/IN2",
      "label": "Port",
      "props": {
        "tag": "IN2",
        "modify": false
      }
    },
    {
      "id": "inputs:galaxian/IN2/f0",
      "label": "PortField",
      "props": {
        "kind": "dip",
        "mask": 3,
        "name": "Bonus Life",
        "defaultValue": 0,
        "settings": [
          "0=7000",
          "1=10000",
          "2=12000",
          "3=20000"
        ]
      }
    },
    {
      "id": "inputs:galaxian/IN2/f1",
      "label": "PortField",
      "props": {
        "kind": "dip",
        "mask": 4,
        "name": "Lives",
        "defaultValue": 4,
        "settings": [
          "0=2",
          "4=3"
        ]
      }
    },
    {
      "id": "inputs:galaxian/IN2/f2",
      "label": "PortField",
      "props": {
        "kind": "bit",
        "mask": 240,
        "activeLow": false,
        "type": "IPT_UNUSED"
      }
    },
    {
      "id": "gfxlayout:galaxian_charlayout",
      "label": "GfxLayout",
      "props": {
        "name": "galaxian_charlayout",
        "width": 8,
        "height": 8,
        "total": "RGN_FRAC(1,2)",
        "planes": 2,
        "planeOffsets": [
          "RGN_FRAC(0,2)",
          "RGN_FRAC(1,2)"
        ],
        "xOffsets": [
          0,
          1,
          2,
          3,
          4,
          5,
          6,
          7
        ],
        "yOffsets": [
          0,
          8,
          16,
          24,
          32,
          40,
          48,
          56
        ],
        "charIncrement": 64
      }
    },
    {
      "id": "gfxlayout:galaxian_spritelayout",
      "label": "GfxLayout",
      "props": {
        "name": "galaxian_spritelayout",
        "width": 16,
        "height": 16,
        "total": "RGN_FRAC(1,2)",
        "planes": 2,
        "planeOffsets": [
          "RGN_FRAC(0,2)",
          "RGN_FRAC(1,2)"
        ],
        "xOffsets": [
          0,
          1,
          2,
          3,
          4,
          5,
          6,
          7,
          64,
          65,
          66,
          67,
          68,
          69,
          70,
          71
        ],
        "yOffsets": [
          0,
          8,
          16,
          24,
          32,
          40,
          48,
          56,
          128,
          136,
          144,
          152,
          160,
          168,
          176,
          184
        ],
        "charIncrement": 256
      }
    },
    {
      "id": "gfxdecode:gfx_galaxian",
      "label": "GfxDecode",
      "props": {
        "name": "gfx_galaxian"
      }
    },
    {
      "id": "gfxdecode:gfx_galaxian/e0",
      "label": "GfxDecodeEntry",
      "props": {
        "region": "gfx1",
        "offset": 0,
        "layout": "galaxian_charlayout",
        "colorBase": 0,
        "colorCount": 8,
        "xscale": 3,
        "yscale": 1
      }
    },
    {
      "id": "gfxdecode:gfx_galaxian/e1",
      "label": "GfxDecodeEntry",
      "props": {
        "region": "gfx1",
        "offset": 0,
        "layout": "galaxian_spritelayout",
        "colorBase": 0,
        "colorCount": 8,
        "xscale": 3,
        "yscale": 1
      }
    }
  ],
  "edges": [
    {
      "from": "game:galaxian",
      "to": "file:src/mame/galaxian/galaxian.cpp",
      "rel": "DEFINED_IN"
    },
    {
      "from": "game:galaxian",
      "to": "machine:galaxian_state.galaxian",
      "rel": "USES_MACHINE"
    },
    {
      "from": "game:galaxian",
      "to": "inputs:galaxian",
      "rel": "USES_INPUTS"
    },
    {
      "from": "game:galaxian",
      "to": "romset:galaxian",
      "rel": "USES_ROMSET"
    },
    {
      "from": "file:src/mame/galaxian/galaxian.cpp",
      "to": "file:emu.h",
      "rel": "INCLUDES"
    },
    {
      "from": "file:src/mame/galaxian/galaxian.cpp",
      "to": "file:galaxian.h",
      "rel": "INCLUDES"
    },
    {
      "from": "file:src/mame/galaxian/galaxian.cpp",
      "to": "file:galaxian_a.h",
      "rel": "INCLUDES"
    },
    {
      "from": "file:src/mame/galaxian/galaxian.cpp",
      "to": "file:cclimber_a.h",
      "rel": "INCLUDES"
    },
    {
      "from": "file:src/mame/galaxian/galaxian.cpp",
      "to": "file:cpu/m6502/m6502.h",
      "rel": "INCLUDES"
    },
    {
      "from": "file:src/mame/galaxian/galaxian.cpp",
      "to": "file:cpu/s2650/s2650.h",
      "rel": "INCLUDES"
    },
    {
      "from": "file:src/mame/galaxian/galaxian.cpp",
      "to": "file:cpu/z80/z80.h",
      "rel": "INCLUDES"
    },
    {
      "from": "file:src/mame/galaxian/galaxian.cpp",
      "to": "file:machine/nvram.h",
      "rel": "INCLUDES"
    },
    {
      "from": "file:src/mame/galaxian/galaxian.cpp",
      "to": "file:machine/watchdog.h",
      "rel": "INCLUDES"
    },
    {
      "from": "file:src/mame/galaxian/galaxian.cpp",
      "to": "file:screen.h",
      "rel": "INCLUDES"
    },
    {
      "from": "file:src/mame/galaxian/galaxian.cpp",
      "to": "file:speaker.h",
      "rel": "INCLUDES"
    },
    {
      "from": "file:src/mame/galaxian/galaxian.cpp",
      "to": "file:nl_konami.h",
      "rel": "INCLUDES"
    },
    {
      "from": "machine:galaxian_state.galaxian",
      "to": "file:src/mame/galaxian/galaxian.cpp",
      "rel": "DEFINED_IN"
    },
    {
      "from": "machine:galaxian_state.galaxian",
      "to": "machine:galaxian_state.galaxian_base",
      "rel": "CALLS"
    },
    {
      "from": "machine:galaxian_state.galaxian",
      "to": "device:galaxian_state.galaxian/cust",
      "rel": "HAS_DEVICE"
    },
    {
      "from": "inputs:galaxian",
      "to": "file:src/mame/galaxian/galaxian.cpp",
      "rel": "DEFINED_IN"
    },
    {
      "from": "inputs:galaxian",
      "to": "inputs:galaxian/IN0",
      "rel": "HAS_PORT"
    },
    {
      "from": "inputs:galaxian",
      "to": "inputs:galaxian/IN1",
      "rel": "HAS_PORT"
    },
    {
      "from": "inputs:galaxian",
      "to": "inputs:galaxian/IN2",
      "rel": "HAS_PORT"
    },
    {
      "from": "romset:galaxian",
      "to": "file:src/mame/galaxian/galaxian.cpp",
      "rel": "DEFINED_IN"
    },
    {
      "from": "romset:galaxian",
      "to": "region:galaxian/maincpu",
      "rel": "HAS_REGION"
    },
    {
      "from": "romset:galaxian",
      "to": "region:galaxian/gfx1",
      "rel": "HAS_REGION"
    },
    {
      "from": "romset:galaxian",
      "to": "region:galaxian/proms",
      "rel": "HAS_REGION"
    },
    {
      "from": "machine:galaxian_state.galaxian_base",
      "to": "file:src/mame/galaxian/galaxian.cpp",
      "rel": "DEFINED_IN"
    },
    {
      "from": "machine:galaxian_state.galaxian_base",
      "to": "device:galaxian_state.galaxian_base/maincpu",
      "rel": "HAS_DEVICE"
    },
    {
      "from": "machine:galaxian_state.galaxian_base",
      "to": "device:galaxian_state.galaxian_base/watchdog",
      "rel": "HAS_DEVICE"
    },
    {
      "from": "machine:galaxian_state.galaxian_base",
      "to": "device:galaxian_state.galaxian_base/gfxdecode",
      "rel": "HAS_DEVICE"
    },
    {
      "from": "machine:galaxian_state.galaxian_base",
      "to": "gfxdecode:gfx_galaxian",
      "rel": "DECODES"
    },
    {
      "from": "machine:galaxian_state.galaxian_base",
      "to": "device:galaxian_state.galaxian_base/palette",
      "rel": "HAS_DEVICE"
    },
    {
      "from": "machine:galaxian_state.galaxian_base",
      "to": "device:galaxian_state.galaxian_base/screen",
      "rel": "HAS_DEVICE"
    },
    {
      "from": "machine:galaxian_state.galaxian_base",
      "to": "device:galaxian_state.galaxian_base/speaker",
      "rel": "HAS_DEVICE"
    },
    {
      "from": "device:galaxian_state.galaxian/cust",
      "to": "machine:galaxian_sound_device.device_add_mconfig",
      "rel": "CALLS"
    },
    {
      "from": "inputs:galaxian/IN0",
      "to": "inputs:galaxian/IN0/f0",
      "rel": "HAS_FIELD"
    },
    {
      "from": "inputs:galaxian/IN0",
      "to": "inputs:galaxian/IN0/f1",
      "rel": "HAS_FIELD"
    },
    {
      "from": "inputs:galaxian/IN0",
      "to": "inputs:galaxian/IN0/f2",
      "rel": "HAS_FIELD"
    },
    {
      "from": "inputs:galaxian/IN0",
      "to": "inputs:galaxian/IN0/f3",
      "rel": "HAS_FIELD"
    },
    {
      "from": "inputs:galaxian/IN0",
      "to": "inputs:galaxian/IN0/f4",
      "rel": "HAS_FIELD"
    },
    {
      "from": "inputs:galaxian/IN0",
      "to": "inputs:galaxian/IN0/f5",
      "rel": "HAS_FIELD"
    },
    {
      "from": "inputs:galaxian/IN0",
      "to": "inputs:galaxian/IN0/f6",
      "rel": "HAS_FIELD"
    },
    {
      "from": "inputs:galaxian/IN0",
      "to": "inputs:galaxian/IN0/f7",
      "rel": "HAS_FIELD"
    },
    {
      "from": "inputs:galaxian/IN1",
      "to": "inputs:galaxian/IN1/f0",
      "rel": "HAS_FIELD"
    },
    {
      "from": "inputs:galaxian/IN1",
      "to": "inputs:galaxian/IN1/f1",
      "rel": "HAS_FIELD"
    },
    {
      "from": "inputs:galaxian/IN1",
      "to": "inputs:galaxian/IN1/f2",
      "rel": "HAS_FIELD"
    },
    {
      "from": "inputs:galaxian/IN1",
      "to": "inputs:galaxian/IN1/f3",
      "rel": "HAS_FIELD"
    },
    {
      "from": "inputs:galaxian/IN1",
      "to": "inputs:galaxian/IN1/f4",
      "rel": "HAS_FIELD"
    },
    {
      "from": "inputs:galaxian/IN1",
      "to": "inputs:galaxian/IN1/f5",
      "rel": "HAS_FIELD"
    },
    {
      "from": "inputs:galaxian/IN1",
      "to": "inputs:galaxian/IN1/f6",
      "rel": "HAS_FIELD"
    },
    {
      "from": "inputs:galaxian/IN2",
      "to": "inputs:galaxian/IN2/f0",
      "rel": "HAS_FIELD"
    },
    {
      "from": "inputs:galaxian/IN2",
      "to": "inputs:galaxian/IN2/f1",
      "rel": "HAS_FIELD"
    },
    {
      "from": "inputs:galaxian/IN2",
      "to": "inputs:galaxian/IN2/f2",
      "rel": "HAS_FIELD"
    },
    {
      "from": "region:galaxian/maincpu",
      "to": "rom:galaxian/maincpu/galmidw.u",
      "rel": "LOADS"
    },
    {
      "from": "region:galaxian/maincpu",
      "to": "rom:galaxian/maincpu/galmidw.v",
      "rel": "LOADS"
    },
    {
      "from": "region:galaxian/maincpu",
      "to": "rom:galaxian/maincpu/galmidw.w",
      "rel": "LOADS"
    },
    {
      "from": "region:galaxian/maincpu",
      "to": "rom:galaxian/maincpu/galmidw.y",
      "rel": "LOADS"
    },
    {
      "from": "region:galaxian/maincpu",
      "to": "rom:galaxian/maincpu/7l",
      "rel": "LOADS"
    },
    {
      "from": "region:galaxian/gfx1",
      "to": "rom:galaxian/gfx1/1h.bin",
      "rel": "LOADS"
    },
    {
      "from": "region:galaxian/gfx1",
      "to": "rom:galaxian/gfx1/1k.bin",
      "rel": "LOADS"
    },
    {
      "from": "region:galaxian/proms",
      "to": "rom:galaxian/proms/6l.bpr",
      "rel": "LOADS"
    },
    {
      "from": "device:galaxian_state.galaxian_base/maincpu",
      "to": "map:galaxian_state.galaxian_map",
      "rel": "HAS_MAP",
      "props": {
        "space": "AS_PROGRAM"
      }
    },
    {
      "from": "gfxdecode:gfx_galaxian",
      "to": "file:src/mame/galaxian/galaxian.cpp",
      "rel": "DEFINED_IN"
    },
    {
      "from": "gfxdecode:gfx_galaxian",
      "to": "gfxdecode:gfx_galaxian/e0",
      "rel": "HAS_ENTRY"
    },
    {
      "from": "gfxdecode:gfx_galaxian",
      "to": "gfxdecode:gfx_galaxian/e1",
      "rel": "HAS_ENTRY"
    },
    {
      "from": "machine:galaxian_sound_device.device_add_mconfig",
      "to": "file:src/mame/galaxian/galaxian.cpp",
      "rel": "DEFINED_IN"
    },
    {
      "from": "machine:galaxian_sound_device.device_add_mconfig",
      "to": "device:galaxian_sound_device.device_add_mconfig/discrete",
      "rel": "HAS_DEVICE"
    },
    {
      "from": "map:galaxian_state.galaxian_map",
      "to": "file:src/mame/galaxian/galaxian.cpp",
      "rel": "DEFINED_IN"
    },
    {
      "from": "map:galaxian_state.galaxian_map",
      "to": "map:galaxian_state.galaxian_map_base",
      "rel": "INCLUDES_MAP"
    },
    {
      "from": "map:galaxian_state.galaxian_map",
      "to": "map:galaxian_state.galaxian_map_discrete",
      "rel": "INCLUDES_MAP"
    },
    {
      "from": "gfxdecode:gfx_galaxian/e0",
      "to": "gfxlayout:galaxian_charlayout",
      "rel": "USES_LAYOUT"
    },
    {
      "from": "gfxdecode:gfx_galaxian/e1",
      "to": "gfxlayout:galaxian_spritelayout",
      "rel": "USES_LAYOUT"
    },
    {
      "from": "map:galaxian_state.galaxian_map_base",
      "to": "file:src/mame/galaxian/galaxian.cpp",
      "rel": "DEFINED_IN"
    },
    {
      "from": "map:galaxian_state.galaxian_map_base",
      "to": "map:galaxian_state.galaxian_map_base/range0",
      "rel": "HAS_RANGE"
    },
    {
      "from": "map:galaxian_state.galaxian_map_base",
      "to": "map:galaxian_state.galaxian_map_base/range1",
      "rel": "HAS_RANGE"
    },
    {
      "from": "map:galaxian_state.galaxian_map_base",
      "to": "map:galaxian_state.galaxian_map_base/range2",
      "rel": "HAS_RANGE"
    },
    {
      "from": "map:galaxian_state.galaxian_map_base",
      "to": "map:galaxian_state.galaxian_map_base/range3",
      "rel": "HAS_RANGE"
    },
    {
      "from": "map:galaxian_state.galaxian_map_base",
      "to": "map:galaxian_state.galaxian_map_base/range4",
      "rel": "HAS_RANGE"
    },
    {
      "from": "map:galaxian_state.galaxian_map_base",
      "to": "map:galaxian_state.galaxian_map_base/range5",
      "rel": "HAS_RANGE"
    },
    {
      "from": "map:galaxian_state.galaxian_map_base",
      "to": "map:galaxian_state.galaxian_map_base/range6",
      "rel": "HAS_RANGE"
    },
    {
      "from": "map:galaxian_state.galaxian_map_base",
      "to": "map:galaxian_state.galaxian_map_base/range7",
      "rel": "HAS_RANGE"
    },
    {
      "from": "map:galaxian_state.galaxian_map_base",
      "to": "map:galaxian_state.galaxian_map_base/range8",
      "rel": "HAS_RANGE"
    },
    {
      "from": "map:galaxian_state.galaxian_map_base",
      "to": "map:galaxian_state.galaxian_map_base/range9",
      "rel": "HAS_RANGE"
    },
    {
      "from": "map:galaxian_state.galaxian_map_base",
      "to": "map:galaxian_state.galaxian_map_base/range10",
      "rel": "HAS_RANGE"
    },
    {
      "from": "map:galaxian_state.galaxian_map_base",
      "to": "map:galaxian_state.galaxian_map_base/range11",
      "rel": "HAS_RANGE"
    },
    {
      "from": "map:galaxian_state.galaxian_map_base",
      "to": "map:galaxian_state.galaxian_map_base/range12",
      "rel": "HAS_RANGE"
    },
    {
      "from": "map:galaxian_state.galaxian_map_base",
      "to": "map:galaxian_state.galaxian_map_base/range13",
      "rel": "HAS_RANGE"
    },
    {
      "from": "map:galaxian_state.galaxian_map_base",
      "to": "map:galaxian_state.galaxian_map_base/range14",
      "rel": "HAS_RANGE"
    },
    {
      "from": "map:galaxian_state.galaxian_map_discrete",
      "to": "file:src/mame/galaxian/galaxian.cpp",
      "rel": "DEFINED_IN"
    },
    {
      "from": "map:galaxian_state.galaxian_map_discrete",
      "to": "map:galaxian_state.galaxian_map_discrete/range0",
      "rel": "HAS_RANGE"
    },
    {
      "from": "map:galaxian_state.galaxian_map_discrete",
      "to": "map:galaxian_state.galaxian_map_discrete/range1",
      "rel": "HAS_RANGE"
    },
    {
      "from": "map:galaxian_state.galaxian_map_discrete",
      "to": "map:galaxian_state.galaxian_map_discrete/range2",
      "rel": "HAS_RANGE"
    },
    {
      "from": "gfxlayout:galaxian_charlayout",
      "to": "file:src/mame/galaxian/galaxian.cpp",
      "rel": "DEFINED_IN"
    },
    {
      "from": "gfxlayout:galaxian_spritelayout",
      "to": "file:src/mame/galaxian/galaxian.cpp",
      "rel": "DEFINED_IN"
    },
    {
      "from": "map:galaxian_state.galaxian_map_base/range2",
      "to": "handler:galaxian_state.galaxian_videoram_w",
      "rel": "WRITES"
    },
    {
      "from": "map:galaxian_state.galaxian_map_base/range3",
      "to": "handler:galaxian_state.galaxian_objram_w",
      "rel": "WRITES"
    },
    {
      "from": "map:galaxian_state.galaxian_map_base/range5",
      "to": "handler:galaxian_state.start_lamp_w",
      "rel": "WRITES"
    },
    {
      "from": "map:galaxian_state.galaxian_map_base/range6",
      "to": "handler:galaxian_state.coin_lock_w",
      "rel": "WRITES"
    },
    {
      "from": "map:galaxian_state.galaxian_map_base/range7",
      "to": "handler:galaxian_state.coin_count_0_w",
      "rel": "WRITES"
    },
    {
      "from": "map:galaxian_state.galaxian_map_base/range10",
      "to": "handler:galaxian_state.irq_enable_w",
      "rel": "WRITES"
    },
    {
      "from": "map:galaxian_state.galaxian_map_base/range11",
      "to": "handler:galaxian_state.galaxian_stars_enable_w",
      "rel": "WRITES"
    },
    {
      "from": "map:galaxian_state.galaxian_map_base/range12",
      "to": "handler:galaxian_state.galaxian_flip_screen_x_w",
      "rel": "WRITES"
    },
    {
      "from": "map:galaxian_state.galaxian_map_base/range13",
      "to": "handler:galaxian_state.galaxian_flip_screen_y_w",
      "rel": "WRITES"
    },
    {
      "from": "map:galaxian_state.galaxian_map_base/range14",
      "to": "handler:watchdog_timer_device.reset_r",
      "rel": "READS",
      "props": {
        "deviceTag": "watchdog"
      }
    },
    {
      "from": "map:galaxian_state.galaxian_map_discrete/range0",
      "to": "handler:galaxian_sound_device.lfo_freq_w",
      "rel": "WRITES",
      "props": {
        "deviceTag": "cust"
      }
    },
    {
      "from": "map:galaxian_state.galaxian_map_discrete/range1",
      "to": "handler:galaxian_sound_device.sound_w",
      "rel": "WRITES",
      "props": {
        "deviceTag": "cust"
      }
    },
    {
      "from": "map:galaxian_state.galaxian_map_discrete/range2",
      "to": "handler:galaxian_sound_device.pitch_w",
      "rel": "WRITES",
      "props": {
        "deviceTag": "cust"
      }
    }
  ]
}